LICENSE
MANIFEST.in
README.md
setup.py
docs/User-Guide.md
pyngus/__init__.py
pyngus/connection.py
pyngus/container.py
pyngus/endpoint.py
pyngus/link.py
pyngus/sockets.py
pyngus.egg-info/PKG-INFO
pyngus.egg-info/SOURCES.txt
pyngus.egg-info/dependency_links.txt
pyngus.egg-info/requires.txt
pyngus.egg-info/top_level.txt